machinecommander/__init__.py
machinecommander/mcp_server.py
machinecommander-0.2.0.dist-info/METADATA
machinecommander-0.2.0.dist-info/WHEEL
machinecommander-0.2.0.dist-info/entry_points.txt
machinecommander-0.2.0.dist-info/RECORD
