Metadata-Version: 2.4
Name: machinecommander
Version: 0.2.0
Summary: MachineCommander is an IoT system to manage all the construction machines working on construction projects.
Author-email: Ye Wang <wangye@zeaho.com>
Requires-Python: >=3.12
Requires-Dist: mcp>=1.10.1
Requires-Dist: requests>=2.31.0
